.coveragerc
.gitignore
.gitmodules
CMakeLists.txt
LICENSE
MANIFEST.in
README.md
setup.cfg
setup.py
.github/workflows/building-conda.yml
.github/workflows/building.yml
.github/workflows/linting.yml
.github/workflows/metis-Windows.sh
.github/workflows/metis.sh
.github/workflows/stale.yml
.github/workflows/testing.yml
.github/workflows/cuda/cu101-Linux-env.sh
.github/workflows/cuda/cu101-Linux.sh
.github/workflows/cuda/cu101-Windows-env.sh
.github/workflows/cuda/cu101-Windows.sh
.github/workflows/cuda/cu102-Linux-env.sh
.github/workflows/cuda/cu102-Linux.sh
.github/workflows/cuda/cu102-Windows-env.sh
.github/workflows/cuda/cu102-Windows.sh
.github/workflows/cuda/cu111-Linux-env.sh
.github/workflows/cuda/cu111-Linux.sh
.github/workflows/cuda/cu111-Windows-env.sh
.github/workflows/cuda/cu111-Windows.sh
.github/workflows/cuda/cu113-Linux-env.sh
.github/workflows/cuda/cu113-Linux.sh
.github/workflows/cuda/cu113-Windows-env.sh
.github/workflows/cuda/cu113-Windows.sh
.github/workflows/cuda/cu115-Linux-env.sh
.github/workflows/cuda/cu115-Linux.sh
.github/workflows/cuda/cu115-Windows-env.sh
.github/workflows/cuda/cu115-Windows.sh
.github/workflows/cuda/cu116-Linux-env.sh
.github/workflows/cuda/cu116-Linux.sh
.github/workflows/cuda/cu116-Windows-env.sh
.github/workflows/cuda/cu116-Windows.sh
.github/workflows/cuda/cu117-Linux-env.sh
.github/workflows/cuda/cu117-Linux.sh
.github/workflows/cuda/cu117-Windows-env.sh
.github/workflows/cuda/cu117-Windows.sh
.github/workflows/cuda/cu118-Linux-env.sh
.github/workflows/cuda/cu118-Linux.sh
.github/workflows/cuda/cu118-Windows-env.sh
.github/workflows/cuda/cu118-Windows.sh
.github/workflows/cuda/cu121-Linux-env.sh
.github/workflows/cuda/cu121-Linux.sh
.github/workflows/cuda/cu121-Windows-env.sh
.github/workflows/cuda/cu121-Windows.sh
cmake/FindMetis.cmake
cmake/TorchSparseConfig.cmake.in
conda/pytorch-sparse/README.md
conda/pytorch-sparse/bld.bat
conda/pytorch-sparse/build.sh
conda/pytorch-sparse/build_conda.sh
torch_sparse.egg-info/PKG-INFO
torch_sparse.egg-info/SOURCES.txt
torch_sparse.egg-info/dependency_links.txt
torch_sparse.egg-info/requires.txt
torch_sparse.egg-info/top_level.txt