Metadata-Version: 2.1
Name: torch-sparse
Version: 0.6.18
Summary: PyTorch Extension Library of Optimized Autograd Sparse Matrix Operations
Home-page: https://github.com/rusty1s/pytorch_sparse
Download-URL: https://github.com/rusty1s/pytorch_sparse/archive/0.6.18.tar.gz
Author: Matthias Fey
Author-email: matthias.fey@tu-dortmund.de
License: UNKNOWN
Keywords: pytorch,sparse,sparse-matrices,autograd
Platform: UNKNOWN
Classifier: Development Status :: 5 - Production/Stable
Classifier: License :: OSI Approved :: MIT License
Classifier: Programming Language :: Python
Classifier: Programming Language :: Python :: 3.8
Classifier: Programming Language :: Python :: 3.9
Classifier: Programming Language :: Python :: 3.10
Classifier: Programming Language :: Python :: 3.11
Classifier: Programming Language :: Python :: 3 :: Only
Requires-Python: >=3.8
Provides-Extra: test
License-File: LICENSE
